LICENSE
MANIFEST.in
README.rst
setup.py
tests.py
FeinCMS_Blogs.egg-info/PKG-INFO
FeinCMS_Blogs.egg-info/SOURCES.txt
FeinCMS_Blogs.egg-info/dependency_links.txt
FeinCMS_Blogs.egg-info/requires.txt
FeinCMS_Blogs.egg-info/top_level.txt
blogs/__init__.py
blogs/abstract_models.py
blogs/admin.py
blogs/content.py
blogs/models.py
blogs/urls.py
blogs/views.py
blogs/templatetags/__init__.py
blogs/templatetags/blogs.py