Metadata-Version: 1.0
Name: FeinCMS-Blogs
Version: 0.0.4
Summary: Multiple blog/article app for Django/FeinCMS.
Home-page: https://github.com/fah-designs/feincms-blogs
Author: Richard Ward
Author-email: richard.ward@fah-designs.co.uk
License: BSD
Platform: UNKNOWN
